lastprophet/__init__.py
lastprophet/aggHier.py
lastprophet/fitProphet.py
lastprophet/last.py
lastprophet/plotTemporal.py
lastprophet/reconcile.py
lastprophet-0.1.0.dist-info/DESCRIPTION.rst
lastprophet-0.1.0.dist-info/METADATA
lastprophet-0.1.0.dist-info/RECORD
lastprophet-0.1.0.dist-info/WHEEL
lastprophet-0.1.0.dist-info/metadata.json
lastprophet-0.1.0.dist-info/top_level.txt
