Metadata-Version: 2.0
Name: lastprophet
Version: 0.1.0
Summary: Long and Short Term Time Series Forecasting with Facebook's Prophet tool
Home-page: https://github.com/CollinRooney12/lastprophet
Author: Collin Rooney
Author-email: CollinRooney12@gmail.com
License: MIT
Keywords: last MAPA thief temporal time series hierarchy forecast Prophet
Platform: UNKNOWN
Requires-Dist: fbprophet
Requires-Dist: matplotlib
Requires-Dist: numpy
Requires-Dist: pandas (>=0.18.1)
